bpa_fetch.py
bpa_fetch-1.0.1.dist-info/licenses/LICENSE
bpa_fetch-1.0.1.dist-info/METADATA
bpa_fetch-1.0.1.dist-info/WHEEL
bpa_fetch-1.0.1.dist-info/entry_points.txt
bpa_fetch-1.0.1.dist-info/top_level.txt
bpa_fetch-1.0.1.dist-info/RECORD
