Metadata-Version: 2.4
Name: bpa-fetch
Version: 1.0.1
Summary: A tool to download and parse historical BPA transmission data 
License-Expression: MIT
Project-URL: Home, https://github.com/goose-den/bpa-fetch
Requires-Python: >=3.12
License-File: LICENSE
Requires-Dist: beautifulsoup4
Requires-Dist: pandas
Requires-Dist: openpyxl
Requires-Dist: requests
Requires-Dist: urllib3
Requires-Dist: numpy
Requires-Dist: pyarrow
Requires-Dist: xlrd
Dynamic: license-file
